Workbook

Sheet Cover
B2: Jarir Marketing Company (TADAWUL: 4190)
B3: Illustrative Leveraged Buyout (LBO) Analysis
B4: Prepared for practice purposes — PE Deal Process & LBO Modeling
B6: Contents
B7: 1. Assumptions
B8: 2. Sources & Uses
B9: 3. Operating Model
B10: 4. Debt Schedule & Free Cash Flow
B11: 5. Returns Analysis & Sensitivity
B14: Key Notes
B15: All figures in SAR millions unless noted otherwise.
B16: Entry valuation set at Jarir's current public market EV/EBITDA (~15.0x) to reflect a realistic take-private scenario.
... B19: Historical FY2025A figures sourced from company financial statements / market data (see cell notes).

Sheet Assumptions
A1: Assumptions (SAR mm unless noted)
A3: Transaction Assumptions
A4: FY2025A Revenue | B4: 11365 | C4: Source: stockanalysis.com, FY2025 Income Statement, Dec-2025
A5: FY2025A EBITDA | B5: 1186 | C5: Source: stockanalysis.com, FY2025 Income Statement (EBITDA margin 10.44%)
A6: Existing Net Debt at Entry | B6: 621 | C6: Source: stockanalysis.com Statistics; Debt SAR 813mm less Cash SAR 191mm
A7: Entry EV / EBITDA Multiple | B7: 15 | C7: Approximates current Tadawul trading multiple (EV/EBITDA)
A8: Transaction Fees (% of EV) | B8: 0.02 | C8: Illustrative advisory/financing fee assumption
A9: Exit Year (Hold Period) | B9: 5 | C9: Standard PE hold period
A10: Exit EV / EBITDA Multiple (Base Case) | B10: 15 | C10: Base case assumes exit at entry multiple (no re-rating)
A12: Financing Assumptions
A13: Senior Term Loan (x FY2025A EBITDA) | B13: 4 | C13: Sized to keep leverage moderate given already-rich entry price
A14: Term Loan Interest Rate (all-in) | B14: 0.085 | C14: Illustrative SAIBOR + margin for SAR-denominated facility
A15: Mandatory Amortization (% of original balance p.a.) | B15: 0.01 | C15: Typical covenant-lite TLB amortization
A16: Cash Sweep (% of excess FCF) | B16: 0.75 | C16: Post mandatory amort., pre minimum cash
A17: Minimum Cash Balance | B17: 200 | C17: Operating cash buffer retained, not swept
A19: Operating Assumptions
A20: Revenue Growth — Year 1 | B20: 0.05 | C20: Above trend; reflects post-close showroom expansion
A21: Revenue Growth — Year 2-5 | B21: 0.04 | C21: In line with analyst consensus (~3.6%-4.4% p.a.)
A22: EBITDA Margin (held flat, all years) | B22: 0.105 | C22: Slightly above FY2025A 10.44% margin
A23: D&A (% of Revenue) | B23: 0.006 | C23: Asset-light retail model, low capex intensity
A24: Capex (% of Revenue) | B24: 0.01 | C24: In line with historical capex/revenue
A25: Increase in NWC (% of Revenue growth) | B25: 0.08 | C25: Inventory build funded partly by supplier credit
A26: Effective Tax Rate (Zakat) | B26: 0.03 | C26: Reflects historical effective Zakat rate ~2.6%-3.0%

Sheet Sources & Uses
A1: Sources & Uses of Funds (SAR mm)
A3: Sources | D3: Sources
A4: Purchase Enterprise Value | B4: =Assumptions!$B$5*Assumptions!$B$7 -> 17790 | D4: New Senior Term Loan | E4: =Assumptions!$B$5*Assumptions!$B$13 -> 4744
A5: Repay Existing Net Debt | B5: =Assumptions!$B$6 -> 621 | D5: Sponsor Equity (plug) | E5: =B7-E4 -> 14022.8
A6: Transaction Fees & Expenses | B6: =B4*Assumptions!$B$8 -> 355.8
A7: Total Uses | B7: =SUM(B4:B6) -> 18766.8 | D7: Total Sources | E7: =SUM(E4:E6) -> 18766.8
A9: Check (Sources - Uses) | B9: =E7-B7 -> 0
A11: Implied Leverage & Equity Metrics
A12: Total Debt / EBITDA (Entry) | B12: =E4/Assumptions!$B$5 -> 4
A13: Equity Contribution (% of Total Sources) | B13: =E5/E7 -> 0.74721316
A14: Entry EV / EBITDA | B14: =Assumptions!$B$7 -> 15

Sheet Operating Model & Debt Schedule
A1: Operating Model, Debt Schedule & Free Cash Flow (SAR mm)
A3: Period | B3: FY2025A / At Close | C3: Year 1 | D3: Year 2 | E3: Year 3 | F3: Year 4 | G3: Year 5
A5: Operating Model
A6: Revenue | B6: =Assumptions!$B$4 -> 11365 | C6: =B6*(1+Assumptions!$B$20) -> 11933.25 | D6: =C6*(1+Assumptions!$B$21) -> 12410.58 | E6: =D6*(1+Assumptions!$B$21) -> 12907.003 | F6: =E6*(1+Assumptions!$B$21) -> 13423.283 | G6: =F6*(1+Assumptions!$B$21) -> 13960.215
A7: Revenue Growth % | C7: =Assumptions!$B$20 -> 0.05 | D7: =Assumptions!$B$21 -> 0.04 | E7: =Assumptions!$B$21 -> 0.04 | F7: =Assumptions!$B$21 -> 0.04 | G7: =Assumptions!$B$21 -> 0.04
A8: EBITDA | B8: =Assumptions!$B$5 -> 1186 | C8: =C6*Assumptions!$B$22 -> 1252.9913 | D8: =D6*Assumptions!$B$22 -> 1303.1109 | E8: =E6*Assumptions!$B$22 -> 1355.2353 | F8: =F6*Assumptions!$B$22 -> 1409.4447 | G8: =G6*Assumptions!$B$22 -> 1465.8225
A9: EBITDA Margin % | B9: =B8/B6 -> 0.10435548 | C9: =C8/C6 -> 0.105 | D9: =D8/D6 -> 0.105 | E9: =E8/E6 -> 0.105 | F9: =F8/F6 -> 0.105 | G9: =G8/G6 -> 0.105
A10: D&A | B10: 61.46 | C10: =C6*Assumptions!$B$23 -> 71.5995 | D10: =D6*Assumptions!$B$23 -> 74.46348 | E10: =E6*Assumptions!$B$23 -> 77.442019 | F10: =F6*Assumptions!$B$23 -> 80.5397 | G10: =G6*Assumptions!$B$23 -> 83.761288
A11: EBIT | B11: =B8-B10 -> 1124.54 | C11: =C8-C10 -> 1181.3918 | D11: =D8-D10 -> 1228.6474 | E11: =E8-E10 -> 1277.7933 | F11: =F8-F10 -> 1328.905 | G11: =G8-G10 -> 1382.0613
A13: Debt Schedule
A14: Beginning Debt Balance | C14: ='Sources & Uses'!$E$4 -> 4744 | D14: =C18 -> 4200.3494 | E14: =D18 -> 3584.679 | F14: =E18 -> 2897.8183 | G14: =F18 -> 2134.0404
A15: Interest Expense | C15: =C14*Assumptions!$B$14 -> 403.24 | D15: =D14*Assumptions!$B$14 -> 357.02969 | E15: =E14*Assumptions!$B$14 -> 304.69771 | F15: =F14*Assumptions!$B$14 -> 246.31456 | G15: =G14*Assumptions!$B$14 -> 181.39344
A16: Mandatory Amortization | C16: =MIN(C14,'Sources & Uses'!$E$4*Assumptions!$B$15) -> 47.44 | D16: =MIN(D14,'Sources & Uses'!$E$4*Assumptions!$B$15) -> 47.44 | E16: =MIN(E14,'Sources & Uses'!$E$4*Assumptions!$B$15) -> 47.44 | F16: =MIN(F14,'Sources & Uses'!$E$4*Assumptions!$B$15) -> 47.44 | G16: =MIN(G14,'Sources & Uses'!$E$4*Assumptions!$B$15) -> 47.44
A17: Optional Cash Sweep | C17: =MAX(MIN(C27*Assumptions!$B$16,C14-C16),0) -> 496.21065 | D17: =MAX(MIN(D27*Assumptions!$B$16,D14-D16),0) -> 568.23036 | E17: =MAX(MIN(E27*Assumptions!$B$16,E14-E16),0) -> 639.42065 | F17: =MAX(MIN(F27*Assumptions!$B$16,F14-F16),0) -> 716.33792 | G17: =MAX(MIN(G27*Assumptions!$B$16,G14-G16),0) -> 799.38931
A18: Ending Debt Balance | B18: ='Sources & Uses'!$E$4 -> 4744 | C18: =C14-C16-C17 -> 4200.3494 | D18: =D14-D16-D17 -> 3584.679 | E18: =E14-E16-E17 -> 2897.8183 | F18: =F14-F16-F17 -> 2134.0404 | G18: =G14-G16-G17 -> 1287.2111
A20: Free Cash Flow & Cash Build
A21: EBT | C21: =C11-C15 -> 778.15175 | D21: =D11-D15 -> 871.61773 | E21: =E11-E15 -> 973.0956 | F21: =F11-F15 -> 1082.5905 | G21: =G11-G15 -> 1200.6678
A22: Taxes (Zakat) | C22: =MAX(C21,0)*Assumptions!$B$26 -> 23.344552 | D22: =MAX(D21,0)*Assumptions!$B$26 -> 26.148532 | E22: =MAX(E21,0)*Assumptions!$B$26 -> 29.192868 | F22: =MAX(F21,0)*Assumptions!$B$26 -> 32.477715 | G22: =MAX(G21,0)*Assumptions!$B$26 -> 36.020034
A23: Net Income | C23: =C21-C22 -> 754.8072 | D23: =D21-D22 -> 845.46919 | E23: =E21-E22 -> 943.90273 | F23: =F21-F22 -> 1050.1128 | G23: =G21-G22 -> 1164.6478
A24: (+) D&A | C24: =C10 -> 71.5995 | D24: =D10 -> 74.46348 | E24: =E10 -> 77.442019 | F24: =F10 -> 80.5397 | G24: =G10 -> 83.761288
A25: (-) Capital Expenditures | C25: =C6*Assumptions!$B$24 -> 119.3325 | D25: =D6*Assumptions!$B$24 -> 124.1058 | E25: =E6*Assumptions!$B$24 -> 129.07003 | F25: =F6*Assumptions!$B$24 -> 134.23283 | G25: =G6*Assumptions!$B$24 -> 139.60215
A26: (-) Increase in NWC | C26: =Assumptions!$B$25*(C6-B6) -> 45.46 | D26: =Assumptions!$B$25*(D6-C6) -> 38.1864 | E26: =Assumptions!$B$25*(E6-D6) -> 39.713856 | F26: =Assumptions!$B$25*(F6-E6) -> 41.30241 | G26: =Assumptions!$B$25*(G6-F6) -> 42.954507
A27: FCF before Debt Service | C27: =C23+C24-C25-C26 -> 661.6142 | D27: =D23+D24-D25-D26 -> 757.64047 | E27: =E23+E24-E25-E26 -> 852.56087 | F27: =F23+F24-F25-F26 -> 955.11723 | G27: =G23+G24-G25-G26 -> 1065.8524
A28: (-) Mandatory Amortization | C28: =C16 -> 47.44 | D28: =D16 -> 47.44 | E28: =E16 -> 47.44 | F28: =F16 -> 47.44 | G28: =G16 -> 47.44
A29: Cash Available for Sweep | C29: =C27-C28 -> 614.1742 | D29: =D27-D28 -> 710.20047 | E29: =E27-E28 -> 805.12087 | F29: =F27-F28 -> 907.67723 | G29: =G27-G28 -> 1018.4124
A30: (-) Optional Cash Sweep | C30: =C17 -> 496.21065 | D30: =D17 -> 568.23036 | E30: =E17 -> 639.42065 | F30: =F17 -> 716.33792 | G30: =G17 -> 799.38931
A31: Cash Build (Retained) | C31: =C29-C30 -> 117.96355 | D31: =D29-D30 -> 141.97012 | E31: =E29-E30 -> 165.70022 | F31: =F29-F30 -> 191.33931 | G31: =G29-G30 -> 219.0231
A32: Beginning Cash Balance | C32: =B33 -> 0 | D32: =C33 -> 117.96355 | E32: =D33 -> 259.93367 | F32: =E33 -> 425.63388 | G32: =F33 -> 616.97319
A33: Ending Cash Balance | B33: 0 | C33: =C32+C31 -> 117.96355 | D33: =D32+D31 -> 259.93367 | E33: =E32+E31 -> 425.63388 | F33: =F32+F31 -> 616.97319 | G33: =G32+G31 -> 835.9963
A35: Memo
A36: Net Debt (Ending Debt - Ending Cash) | B36: =B18-B33 -> 4744 | C36: =C18-C33 -> 4082.3858 | D36: =D18-D33 -> 3324.7453 | E36: =E18-E33 -> 2472.1845 | F36: =F18-F33 -> 1517.0672 | G36: =G18-G33 -> 451.21482
A37: Total Debt / EBITDA | B37: =B18/B8 -> 4 | C37: =C18/C8 -> 3.3522575 | D37: =D18/D8 -> 2.7508626 | E37: =E18/E8 -> 2.13824 | F37: =F18/F8 -> 1.5141001 | G37: =G18/G8 -> 0.87814935

Sheet Returns Analysis
A1: Returns Analysis (Base Case) & Sensitivity
A3: Base Case Exit (Year 5)
A4: Exit Year EBITDA | B4: ='Operating Model & Debt Schedule'!G8 -> 1465.8225
A5: Exit EV / EBITDA Multiple | B5: =Assumptions!$B$10 -> 15
A6: Exit Enterprise Value | B6: =B4*B5 -> 21987.338
A7: Less: Net Debt at Exit | B7: ='Operating Model & Debt Schedule'!G36 -> 451.21482
A8: Exit Equity Value | B8: =B6-B7 -> 21536.123
A10: Sponsor Equity at Entry | B10: ='Sources & Uses'!$E$5 -> 14022.8
A11: Hold Period (Years) | B11: =Assumptions!$B$9 -> 5
A13: MOIC (Exit Equity / Entry Equity) | B13: =B8/B10 -> 1.5357934
A14: IRR | B14: =(B13)^(1/B11)-1 -> 0.089598653
A17: Sensitivity Analysis — MOIC & IRR by Exit Multiple and Entry Leverage
A18: Static snapshot computed by re-running the full model logic for each Exit Multiple / Leverage combination. To make this fully live in Excel, select the base-case MOIC/IRR cells above and use Data > What-If Analysis > Data Table, with Assumptions!B10 (Exit Multiple) as the row input and Assumptions!B13 (Term Loan x) as the column input.
A20: MOIC Grid
A21: Exit Mult. \ Leverage | B21: 3.0x | C21: 3.5x | D21: 4.0x | E21: 4.5x | F21: 5.0x
A22: 12.0x | B22: 1.24 | C22: 1.23 | D22: 1.22 | E22: 1.21 | F22: 1.2
A23: 13.0x | B23: 1.34 | C23: 1.33 | D23: 1.32 | E23: 1.32 | F23: 1.31
A24: 14.0x | B24: 1.43 | C24: 1.43 | D24: 1.43 | E24: 1.43 | F24: 1.43
A25: 15.0x | B25: 1.53 | C25: 1.53 | D25: 1.53 | E25: 1.54 | F25: 1.54
A26: 16.0x | B26: 1.62 | C26: 1.63 | D26: 1.64 | E26: 1.65 | F26: 1.65
A27: 17.0x | B27: 1.72 | C27: 1.73 | D27: 1.74 | E27: 1.75 | F27: 1.77
A28: 18.0x | B28: 1.82 | C28: 1.83 | D28: 1.85 | E28: 1.86 | F28: 1.88
A31: IRR Grid
A32: Exit Mult. \ Leverage | B32: 3.0x | C32: 3.5x | D32: 4.0x | E32: 4.5x | F32: 5.0x
A33: 12.0x | B33: 0.044 | C33: 0.042 | D33: 0.041 | E33: 0.039 | F33: 0.037
A34: 13.0x | B34: 0.06 | C34: 0.059 | D34: 0.058 | E34: 0.057 | F34: 0.056
A35: 14.0x | B35: 0.074 | C35: 0.074 | D35: 0.074 | E35: 0.074 | F35: 0.074
A36: 15.0x | B36: 0.089 | C36: 0.089 | D36: 0.089 | E36: 0.09 | F36: 0.09
A37: 16.0x | B37: 0.102 | C37: 0.103 | D37: 0.104 | E37: 0.105 | F37: 0.106
A38: 17.0x | B38: 0.115 | C38: 0.116 | D38: 0.117 | E38: 0.119 | F38: 0.121
A39: 18.0x | B39: 0.127 | C39: 0.129 | D39: 0.131 | E39: 0.133 | F39: 0.135
A42: Key Takeaway
A43: At Jarir's current market multiple (~15x EV/EBITDA), returns are driven almost entirely by exit multiple assumptions, not leverage — the IRR barely moves across the 3.0x-5.0x leverage range at any given exit multiple, since higher debt reduces the equity check but is offset by higher interest expense against modest 4-5% revenue growth. This suggests Jarir, in its current form, is a weak buyout candidate without a credible path to margin expansion, M&A-driven growth, or multiple re-rating at exit.
